ezib_async/__init__.py
ezib_async/ezib.py
ezib_async/util.py
ezib_async/version.py
ezib_async-0.3.0.dev0.dist-info/licenses/LICENSE
ezib_async-0.3.0.dev0.dist-info/METADATA
ezib_async-0.3.0.dev0.dist-info/WHEEL
ezib_async-0.3.0.dev0.dist-info/top_level.txt
ezib_async-0.3.0.dev0.dist-info/RECORD
