Metadata-Version: 2.4
Name: ezib-async
Version: 0.3.0.dev0
Summary: An asynchronous Python wrapper for Interactive Brokers API based on ib_async, providing a more Pythonic and asyncio-friendly interface.
Classifier: Development Status :: 3 - Alpha
Classifier: Intended Audience :: Developers
Classifier: License :: OSI Approved :: MIT License
Classifier: Programming Language :: Python :: 3.12
Requires-Python: >=3.12
License-File: LICENSE
Requires-Dist: ib-async>=2.0.1
Requires-Dist: pandas>=2.2.3
Provides-Extra: dev
Requires-Dist: pytest-asyncio>=0.26.0; extra == "dev"
Dynamic: license-file
